linknex/__init__.py
linknex/builders.py
linknex/data.py
linknex/metrics/__init__.py
linknex/metrics/paths.py
linknex-0.0.1.dist-info/METADATA
linknex-0.0.1.dist-info/WHEEL
linknex-0.0.1.dist-info/licenses/LICENSE
linknex-0.0.1.dist-info/RECORD
