Metadata-Version: 2.4
Name: linknex
Version: 0.0.1
Summary: LinkNex: Network-of-Networks (NoN) interactions toolkit (MVP)
Author-email: Dan Li <1023533084@qq.com>
License: MIT License
License-File: LICENSE
Classifier: License :: OSI Approved :: MIT License
Classifier: Operating System :: OS Independent
Classifier: Programming Language :: Python :: 3
Requires-Python: >=3.9
Requires-Dist: networkx>=3.0
Requires-Dist: numpy>=1.23
Requires-Dist: scipy>=1.10
